{
    "DataList": [
        {
            "coordinates": [
                {
                    "pt_x": 541,
                    "pt_y": 160,
                    "flag": 1
                },
                {
                    "pt_x": 548,
                    "pt_y": 144,
                    "flag": 1
                },
                {
                    "pt_x": 0,
                    "pt_y": 0,
                    "flag": 0
                },
                {
                    "pt_x": 590,
                    "pt_y": 148,
                    "flag": 1
                },
                {
                    "pt_x": 0,
                    "pt_y": 0,
                    "flag": 0
                },
                {
                    "pt_x": 585,
                    "pt_y": 201,
                    "flag": 1
                },
                {
                    "pt_x": 0,
                    "pt_y": 0,
                    "flag": 0
                },
                {
                    "pt_x": 596,
                    "pt_y": 250,
                    "flag": 1
                },
                {
                    "pt_x": 0,
                    "pt_y": 0,
                    "flag": 0
                },
                {
                    "pt_x": 598,
                    "pt_y": 291,
                    "flag": 1
                },
                {
                    "pt_x": 0,
                    "pt_y": 0,
                    "flag": 0
                },
                {
                    "pt_x": 581,
                    "pt_y": 348,
                    "flag": 1
                },
                {
                    "pt_x": 0,
                    "pt_y": 0,
                    "flag": 0
                },
                {
                    "pt_x": 577,
                    "pt_y": 469,
                    "flag": 1
                },
                {
                    "pt_x": 531,
                    "pt_y": 445,
                    "flag": 1
                },
                {
                    "pt_x": 563,
                    "pt_y": 560,
                    "flag": 1
                },
                {
                    "pt_x": 501,
                    "pt_y": 533,
                    "flag": 1
                },
                {
                    "pt_x": 562,
                    "pt_y": 91,
                    "flag": 1
                },
                {
                    "pt_x": 605,
                    "pt_y": 310,
                    "flag": 1
                },
                {
                    "pt_x": 0,
                    "pt_y": 0,
                    "flag": 0
                },
                {
                    "pt_x": 499,
                    "pt_y": 582,
                    "flag": 1
                },
                {
                    "pt_x": 440,
                    "pt_y": 562,
                    "flag": 1
                }
            ],
            "sex": "Female",
            "distance": "normal",
            "illumination": "day",
            "id_in_image": 1,
            "collecting environment": "Indoor",
            "pose of human body": "Normal-dancing-pose",
            "shooting angle": "Side",
            "age": "child"
        }
    ]
}