{
    "DataList": [
        {
            "coordinates": [
                {
                    "pt_x": 0,
                    "pt_y": 0,
                    "flag": 0
                },
                {
                    "pt_x": 0,
                    "pt_y": 0,
                    "flag": 0
                },
                {
                    "pt_x": 0,
                    "pt_y": 0,
                    "flag": 0
                },
                {
                    "pt_x": 644,
                    "pt_y": 168,
                    "flag": 1
                },
                {
                    "pt_x": 0,
                    "pt_y": 0,
                    "flag": 0
                },
                {
                    "pt_x": 642,
                    "pt_y": 192,
                    "flag": 1
                },
                {
                    "pt_x": 670,
                    "pt_y": 218,
                    "flag": 1
                },
                {
                    "pt_x": 601,
                    "pt_y": 145,
                    "flag": 1
                },
                {
                    "pt_x": 688,
                    "pt_y": 271,
                    "flag": 1
                },
                {
                    "pt_x": 610,
                    "pt_y": 118,
                    "flag": 1
                },
                {
                    "pt_x": 659,
                    "pt_y": 291,
                    "flag": 1
                },
                {
                    "pt_x": 636,
                    "pt_y": 335,
                    "flag": 1
                },
                {
                    "pt_x": 0,
                    "pt_y": 0,
                    "flag": 0
                },
                {
                    "pt_x": 644,
                    "pt_y": 437,
                    "flag": 1
                },
                {
                    "pt_x": 0,
                    "pt_y": 0,
                    "flag": 0
                },
                {
                    "pt_x": 652,
                    "pt_y": 519,
                    "flag": 1
                },
                {
                    "pt_x": 637,
                    "pt_y": 515,
                    "flag": 1
                },
                {
                    "pt_x": 646,
                    "pt_y": 120,
                    "flag": 1
                },
                {
                    "pt_x": 620,
                    "pt_y": 132,
                    "flag": 1
                },
                {
                    "pt_x": 650,
                    "pt_y": 295,
                    "flag": 1
                },
                {
                    "pt_x": 598,
                    "pt_y": 550,
                    "flag": 1
                },
                {
                    "pt_x": 591,
                    "pt_y": 538,
                    "flag": 1
                }
            ],
            "sex": "Male",
            "distance": "normal",
            "illumination": "day",
            "id_in_image": 1,
            "collecting environment": "Indoor",
            "pose of human body": "Normal-dancing-pose",
            "shooting angle": "Side",
            "age": "child"
        }
    ]
}