{
    "DataList": [
        {
            "coordinates": [
                {
                    "pt_x": 677,
                    "pt_y": 169,
                    "flag": 1
                },
                {
                    "pt_x": 692,
                    "pt_y": 158,
                    "flag": 1
                },
                {
                    "pt_x": 668,
                    "pt_y": 159,
                    "flag": 1
                },
                {
                    "pt_x": 712,
                    "pt_y": 174,
                    "flag": 1
                },
                {
                    "pt_x": 0,
                    "pt_y": 0,
                    "flag": 0
                },
                {
                    "pt_x": 724,
                    "pt_y": 216,
                    "flag": 1
                },
                {
                    "pt_x": 654,
                    "pt_y": 233,
                    "flag": 1
                },
                {
                    "pt_x": 722,
                    "pt_y": 232,
                    "flag": 1
                },
                {
                    "pt_x": 616,
                    "pt_y": 329,
                    "flag": 1
                },
                {
                    "pt_x": 702,
                    "pt_y": 239,
                    "flag": 1
                },
                {
                    "pt_x": 629,
                    "pt_y": 271,
                    "flag": 1
                },
                {
                    "pt_x": 718,
                    "pt_y": 371,
                    "flag": 1
                },
                {
                    "pt_x": 642,
                    "pt_y": 375,
                    "flag": 1
                },
                {
                    "pt_x": 692,
                    "pt_y": 521,
                    "flag": 1
                },
                {
                    "pt_x": 639,
                    "pt_y": 517,
                    "flag": 1
                },
                {
                    "pt_x": 707,
                    "pt_y": 629,
                    "flag": 1
                },
                {
                    "pt_x": 640,
                    "pt_y": 628,
                    "flag": 1
                },
                {
                    "pt_x": 684,
                    "pt_y": 127,
                    "flag": 1
                },
                {
                    "pt_x": 696,
                    "pt_y": 268,
                    "flag": 1
                },
                {
                    "pt_x": 635,
                    "pt_y": 246,
                    "flag": 1
                },
                {
                    "pt_x": 716,
                    "pt_y": 672,
                    "flag": 1
                },
                {
                    "pt_x": 613,
                    "pt_y": 663,
                    "flag": 1
                }
            ],
            "sex": "Female",
            "distance": "normal",
            "illumination": "day",
            "id_in_image": 1,
            "collecting environment": "Indoor",
            "pose of human body": "Normal-dancing-pose",
            "shooting angle": "Front",
            "age": "adult"
        }
    ]
}