{
    "DataList": [
        {
            "coordinates": [
                {
                    "pt_x": 713,
                    "pt_y": 211,
                    "flag": 1
                },
                {
                    "pt_x": 0,
                    "pt_y": 0,
                    "flag": 0
                },
                {
                    "pt_x": 702,
                    "pt_y": 204,
                    "flag": 1
                },
                {
                    "pt_x": 0,
                    "pt_y": 0,
                    "flag": 0
                },
                {
                    "pt_x": 0,
                    "pt_y": 0,
                    "flag": 0
                },
                {
                    "pt_x": 0,
                    "pt_y": 0,
                    "flag": 0
                },
                {
                    "pt_x": 671,
                    "pt_y": 246,
                    "flag": 1
                },
                {
                    "pt_x": 0,
                    "pt_y": 0,
                    "flag": 0
                },
                {
                    "pt_x": 746,
                    "pt_y": 243,
                    "flag": 1
                },
                {
                    "pt_x": 0,
                    "pt_y": 0,
                    "flag": 0
                },
                {
                    "pt_x": 810,
                    "pt_y": 240,
                    "flag": 1
                },
                {
                    "pt_x": 0,
                    "pt_y": 0,
                    "flag": 0
                },
                {
                    "pt_x": 685,
                    "pt_y": 367,
                    "flag": 1
                },
                {
                    "pt_x": 0,
                    "pt_y": 0,
                    "flag": 0
                },
                {
                    "pt_x": 704,
                    "pt_y": 474,
                    "flag": 1
                },
                {
                    "pt_x": 0,
                    "pt_y": 0,
                    "flag": 0
                },
                {
                    "pt_x": 681,
                    "pt_y": 563,
                    "flag": 1
                },
                {
                    "pt_x": 688,
                    "pt_y": 172,
                    "flag": 1
                },
                {
                    "pt_x": 836,
                    "pt_y": 232,
                    "flag": 1
                },
                {
                    "pt_x": 728,
                    "pt_y": 295,
                    "flag": 1
                },
                {
                    "pt_x": 726,
                    "pt_y": 573,
                    "flag": 1
                },
                {
                    "pt_x": 726,
                    "pt_y": 581,
                    "flag": 1
                }
            ],
            "sex": "Female",
            "distance": "normal",
            "illumination": "day",
            "id_in_image": 1,
            "collecting environment": "Indoor",
            "pose of human body": "Normal-dancing-pose",
            "shooting angle": "Side",
            "age": "child"
        }
    ]
}